rllama/__init__.py
rllama/agent.py
rllama/memory.py
rllama/scripts.py
rllama-0.1.4.dist-info/LICENSE
rllama-0.1.4.dist-info/METADATA
rllama-0.1.4.dist-info/WHEEL
rllama-0.1.4.dist-info/entry_points.txt
rllama-0.1.4.dist-info/RECORD
