Metadata-Version: 2.1
Name: rllama
Version: 0.1.4
Summary: A reinforcement learning framework for training LLMs featuring memory-augmented learning and multi-modal capabilities (coming soon)
Home-page: https://github.com/ch33nchan/RLlama
License: MIT
Author: ch33nchan
Author-email: ch33nchan@gmail.com
Requires-Python: >=3.8,<4.0
Classifier: License :: OSI Approved :: MIT License
Classifier: Programming Language :: Python :: 3
Classifier: Programming Language :: Python :: 3.8
Classifier: Programming Language :: Python :: 3.9
Classifier: Programming Language :: Python :: 3.10
Classifier: Programming Language :: Python :: 3.11
Classifier: Programming Language :: Python :: 3.12
Requires-Dist: accelerate (>=0.19.0)
Requires-Dist: bitsandbytes (>=0.37.2)
Requires-Dist: gymnasium
Requires-Dist: numpy
Requires-Dist: peft (>=0.3.0)
Requires-Dist: torch (>=2.0.0)
Requires-Dist: tqdm
Requires-Dist: transformers (>=4.28.1)
Requires-Dist: trl (>=0.4.1)
Project-URL: Repository, https://github.com/ch33nchan/RLlama
